auth_app/__init__.py
auth_app/admin.py
auth_app/apps.py
auth_app/auth0backend.py
auth_app/forms.py
auth_app/managers.py
auth_app/models.py
auth_app/urls.py
auth_app/views.py
auth_app/commons/__init__.py
auth_app/commons/kavenegar.py
auth_app/commons/redis.py
auth_app/commons/singleton.py
auth_app/commons/utils.py
auth_app/migrations/0001_initial.py
auth_app/migrations/__init__.py
cnili_authentication-0.0.1.dist-info/LICENCE
cnili_authentication-0.0.1.dist-info/METADATA
cnili_authentication-0.0.1.dist-info/WHEEL
cnili_authentication-0.0.1.dist-info/top_level.txt
cnili_authentication-0.0.1.dist-info/RECORD
