Metadata-Version: 2.1
Name: cnili-authentication
Version: 0.0.1
Summary: Cnili Authentication
Home-page: https://gitlab.com/cnili/cnili-django-auth.git
Author: Cnili Authors
Author-email: info@cnili.com
License: UNKNOWN
Keywords: auth
Platform: UNKNOWN
Classifier: Programming Language :: Python :: 3
Classifier: License :: OSI Approved :: MIT License
Classifier: Operating System :: OS Independent
Requires-Python: >=3.6
License-File: LICENCE
Requires-Dist: social-auth-app-django (==3.1)
Requires-Dist: python-jose (==3.0)
Requires-Dist: django-recaptcha (==2.0.6)
